mcp_server_akshare/__init__.py
mcp_server_akshare/server.py
mcp_server_akshare/wrapper.py
mcp_server_akshare-1.0.0.dist-info/METADATA
mcp_server_akshare-1.0.0.dist-info/WHEEL
mcp_server_akshare-1.0.0.dist-info/entry_points.txt
mcp_server_akshare-1.0.0.dist-info/licenses/LICENSE
mcp_server_akshare-1.0.0.dist-info/RECORD
