Metadata-Version: 2.4
Name: mcp-server-akshare
Version: 1.0.0
Summary: Model Context Protocol server for AkShare financial data APIs
Project-URL: Homepage, https://github.com/yourusername/mcp-server-akshare
Project-URL: Repository, https://github.com/yourusername/mcp-server-akshare
Project-URL: Issues, https://github.com/yourusername/mcp-server-akshare/issues
Author-email: AkShare MCP Server <example@example.com>
License-Expression: MIT
License-File: LICENSE
Keywords: akshare,financial-data,mcp,model-context-protocol
Classifier: Development Status :: 4 - Beta
Classifier: Intended Audience :: Developers
Classifier: License :: OSI Approved :: MIT License
Classifier: Programming Language :: Python :: 3
Classifier: Programming Language :: Python :: 3.8
Classifier: Programming Language :: Python :: 3.9
Classifier: Programming Language :: Python :: 3.10
Classifier: Programming Language :: Python :: 3.11
Classifier: Programming Language :: Python :: 3.12
Classifier: Topic :: Office/Business :: Financial
Classifier: Topic :: Software Development :: Libraries :: Python Modules
Requires-Python: >=3.8
Requires-Dist: akshare>=1.14.0
Requires-Dist: mcp>=1.0.0
Requires-Dist: numpy>=1.24.0
Requires-Dist: pandas>=2.0.0
Requires-Dist: pydantic>=2.0.0
Provides-Extra: dev
Requires-Dist: black>=22.0.0; extra == 'dev'
Requires-Dist: flake8>=4.0.0; extra == 'dev'
Requires-Dist: isort>=5.0.0; extra == 'dev'
Requires-Dist: pytest>=7.0.0; extra == 'dev'
